kopikatapi/__init__.py
kopikatapi/enums.py
kopikatapi/kopikatapi.py
kopikatapi-0.0.2.dist-info/LICENSE
kopikatapi-0.0.2.dist-info/METADATA
kopikatapi-0.0.2.dist-info/WHEEL
kopikatapi-0.0.2.dist-info/RECORD
